rapa/Project.py
rapa/__init__.py
rapa/_var.py
rapa/base.py
rapa/config.py
rapa/rapa.py
rapa/utils.py
rapa/version.py
tests/__init__.py
tests/conf.py
tests/Project/__init__.py
tests/Project/test_Project_initialization.py
tests/base/__init__.py
tests/base/test_base_initialization.py
tests/base/test_parsimonious_reduction.py
tests/utils/__init__.py
tests/utils/test_datarobot_api.py
tests/utils/test_visualization.py
rapa-0.2.0.dist-info/LICENSE
rapa-0.2.0.dist-info/METADATA
rapa-0.2.0.dist-info/WHEEL
rapa-0.2.0.dist-info/top_level.txt
rapa-0.2.0.dist-info/RECORD
