Metadata-Version: 2.1
Name: rapa
Version: 0.2.0
Summary: Robust Automtated Parsimony Analysis
Home-page: https://github.com/FoxoTech/rapa
Author: FOXO Technologies
Author-email: info@foxotechnologies.com
License: MIT
Keywords: feature reduction features datarobot robust automated parsimony analysis
Platform: UNKNOWN
Classifier: Development Status :: 5 - Production/Stable
Classifier: Environment :: Console
Classifier: License :: OSI Approved :: MIT License
Classifier: Programming Language :: Python :: 3.8
Classifier: Topic :: Scientific/Engineering :: Bio-Informatics
Classifier: Topic :: Scientific/Engineering :: Medical Science Apps.
Classifier: Framework :: Jupyter
Classifier: Intended Audience :: Science/Research
Classifier: Intended Audience :: Financial and Insurance Industry
Classifier: Operating System :: MacOS :: MacOS X
Classifier: Operating System :: Microsoft :: Windows
Classifier: Operating System :: POSIX :: Linux
Requires-Python: >=3.8
Requires-Dist: numpy
Requires-Dist: pandas
Requires-Dist: scikit-learn
Requires-Dist: matplotlib
Requires-Dist: datarobot
Requires-Dist: tqdm
Requires-Dist: seaborn
Requires-Dist: sphinxcontrib-apidoc
Requires-Dist: m2r
Requires-Dist: mistune (==0.8.4)
Requires-Dist: nbsphinx
Requires-Dist: myst-parser
